pymilka/__init__.py
pymilka/constants.py
pymilka/logger.py
pymilka/script.py
pymilka/structures.py
pymilka/templates.py
pymilka/user_input.py
pymilka-0.1.0.dist-info/LICENSE
pymilka-0.1.0.dist-info/METADATA
pymilka-0.1.0.dist-info/WHEEL
pymilka-0.1.0.dist-info/entry_points.txt
pymilka-0.1.0.dist-info/top_level.txt
pymilka-0.1.0.dist-info/RECORD
